lqbox/__init__.py
lqbox/ali/__init__.py
lqbox/base/__init__.py
lqbox/bidp/__init__.py
lqbox/canary/__init__.py
lqbox/elihu/__init__.py
lqbox/eureka/__init__.py
lqbox/mc/__init__.py
lqbox/oc/__init__.py
lqbox/open_bidp/__init__.py
lqbox/open_canary/__init__.py
lqbox/open_elihu/__init__.py
lqbox-2.26.0.dist-info/LICENSE
lqbox-2.26.0.dist-info/METADATA
lqbox-2.26.0.dist-info/WHEEL
lqbox-2.26.0.dist-info/RECORD
