Metadata-Version: 2.1
Name: lqbox
Version: 2.26.0
Summary: lqbox
License: MIT
Author: luke9012
Author-email: luke781520097@163.com
Requires-Python: >=3.6
Classifier: License :: OSI Approved :: MIT License
Classifier: Programming Language :: Python :: 3
Classifier: Programming Language :: Python :: 3.6
Classifier: Programming Language :: Python :: 3.7
Classifier: Programming Language :: Python :: 3.8
Classifier: Programming Language :: Python :: 3.9
Classifier: Programming Language :: Python :: 3.10
Classifier: Programming Language :: Python :: 3.11
Classifier: Programming Language :: Python :: 3.12
Classifier: Programming Language :: Python :: 3.13
Requires-Dist: requests (>=2.27.1)
